microdata_extractor/__init__.py
microdata_extractor/microdata_extractor.py
microdata_extractor-0.0.1.dist-info/LICENSE
microdata_extractor-0.0.1.dist-info/METADATA
microdata_extractor-0.0.1.dist-info/WHEEL
microdata_extractor-0.0.1.dist-info/top_level.txt
microdata_extractor-0.0.1.dist-info/RECORD
